MANIFEST.in
README.md
setup.cfg
setup.py
pystilez/__init__.py
pystilez.egg-info/PKG-INFO
pystilez.egg-info/SOURCES.txt
pystilez.egg-info/dependency_links.txt
pystilez.egg-info/top_level.txt